jobx/__init__.py
jobx/build.py
jobx/config.py
jobx/jobx.py
jobx/task.py
jobx/task_runner.py
jobx/utils.py
jobx/builders/__init__.py
jobx/builders/command.py
jobx/builders/python.py
jobx/builders/python_code_runner.py
jobx/builders/registry.py
jobx/builders/task_group.py
jobx/clitools/__init__.py
jobx/clitools/cli.py
jobx-0.0.2.9.dist-info/LICENSE
jobx-0.0.2.9.dist-info/METADATA
jobx-0.0.2.9.dist-info/WHEEL
jobx-0.0.2.9.dist-info/entry_points.txt
jobx-0.0.2.9.dist-info/top_level.txt
jobx-0.0.2.9.dist-info/RECORD
